{"metadata":{"name":"Sahih Muslim","section":{"39":{"eng-name":"The Book of Greetings","ara-name":"كتاب السلام"}},"section_detail":{"39":{"hadithnumber_first":5646,"hadithnumber_last":5861,"arabicnumber_first":2160,"arabicnumber_last":2245.02}}},"hadiths":[{"hadithnumber":5779,"arabicnumber":"2218.08","text":"حدثنا محمد بن المثنى، حدثنا ابن ابي عدي، عن شعبة، عن حبيب، قال كنا بالمدينة فبلغني ان الطاعون قد وقع بالكوفة فقال لي عطاء بن يسار وغيره ان رسول الله صلى الله عليه وسلم قال \" اذا كنت بارض فوقع بها فلا تخرج منها واذا بلغك انه بارض فلا تدخلها \" . قال قلت عمن قالوا عن عامر بن سعد يحدث به . قال فاتيته فقالوا غايب - قال - فلقيت اخاه ابراهيم بن سعد فسالته فقال شهدت اسامة يحدث سعدا قال سمعت رسول الله صلى الله عليه وسلم يقول \" ان هذا الوجع رجز او عذاب او بقية عذاب عذب به اناس من قبلكم فاذا كان بارض وانتم بها فلا تخرجوا منها واذا بلغكم انه بارض فلا تدخلوها \" . قال حبيب فقلت لابراهيم انت سمعت اسامة يحدث سعدا وهو لا ينكر قال نعم","grades":[{"name":"Imam Muslim","grade":"Sahih"}],"reference":{"book":39,"hadith":131},"chapter":{"id":32,"ara-name":"باب الطَّاعُونِ وَالطِّيَرَةِ وَالْكَهَانَةِ وَنَحْوِهَا ","eng-name":"The Plague, Ill Omens, Soothsaying And The Like","isFirstHadith":false}}]}