{"metadata":{"name":"Sahih Muslim","section":{"36":{"eng-name":"The Book of Drinks","ara-name":"كتاب الأشربة"}},"section_detail":{"36":{"hadithnumber_first":5114,"hadithnumber_last":5383,"arabicnumber_first":1979.02,"arabicnumber_last":2064.04}}},"hadiths":[{"hadithnumber":5349,"arabicnumber":"2050","text":"Jâbir Ibn 'Abdoullâh (رضي الله عنهما) a dit : Nous étions avec le Prophète à Marr Az-Zahrân en train de cueillir des Kabâths (les fruits d'arak mûrs). - \"Choisissez les noirs, s'écria l'Envoyé de Dieu (paix et bénédiction de Dieu sur lui), ce sont les meilleurs\". - \"Ô Envoyé de Dieu, alors, lui dit-on, il paraît que tu as gardé les moutons\". - \"Oui, nous répondit-il, y a-t-il un Prophète qui ne les ait pas gardés?\". Le fait de donner hospitalité à l'hôte","grades":[{"name":"Imam Muslim","grade":"Sahih"}],"reference":{"book":36,"hadith":223},"chapter":{"id":29,"ara-name":"باب فَضِيلَةِ الأَسْوَدِ مِنَ الْكَبَاثِ ","eng-name":"The virtue of the black fruit from the Arak tree","isFirstHadith":true}}]}