{"metadata":{"name":"Sahih al Bukhari","section":{"52":{"eng-name":"Witnesses","ara-name":"كتاب الشهادات"}},"section_detail":{"52":{"hadithnumber_first":2637,"hadithnumber_last":2689,"arabicnumber_first":2637,"arabicnumber_last":2689}}},"hadiths":[{"hadithnumber":2663,"arabicnumber":2663,"text":"আবূ মূসা (রাঃ) হতে বর্ণিত। নবী (সাল্লাল্লাহু আলাইহি ওয়াসাল্লাম) এক ব্যক্তিকে অপর এক ব্যক্তির প্রশংসা করতে শুনে বললেন, তোমরা তাকে ধ্বংস করে দিলে কিংবা (রাবীর সন্দেহ) বলেছেন, তোমরা লোকটির মেরুদন্ড ভেঙ্গে ফেললে। (৬০৬০) (মুসলিম ৫৩/১৩ হাঃ ৩০০১, আহমাদ ১৯৭১২) (আধুনিক প্রকাশনীঃ ২৪৭১, ইসলামিক ফাউন্ডেশনঃ)","grades":[{"name":"Imam Bukhari","grade":"Sahih"}],"reference":{"book":52,"hadith":27},"chapter":{"id":17,"ara-name":"باب مَا يُكْرَهُ مِنَ الإِطْنَابِ فِي الْمَدْحِ وَلْيَقُلْ مَا يَعْلَمُ","eng-name":"One should say only what he knows","isFirstHadith":true}}]}