{"metadata":{"name":"Sahih al Bukhari","section":{"55":{"eng-name":"Wills and Testaments (Wasaayaa)","ara-name":"كتاب الوصايا"}},"section_detail":{"55":{"hadithnumber_first":2738,"hadithnumber_last":2781,"arabicnumber_first":2738,"arabicnumber_last":2781}}},"hadiths":[{"hadithnumber":2762,"arabicnumber":2762,"text":"Telah bercerita kepada kami [Ibrahim bin Musa] telah mengabarkan kepada kami [Hisyam bin Yusuf] bahwa [Ibnu Juraij] mengabarkan kepada mereka, dia berkata telah bercerita kepadaku [Ya'laa] bahwa dia mendengar ['Ikrimah. Maula Ibnu 'Abbas] berkata telah memberitakan kepada kami [Ibnu 'Abbas] bahwa Sa'ad bin 'Ubadah radliallahu 'anhum, saudara dari Bani Sa'idah, bahwa ibunya telah meninggal dunia lalu dia datang menemui Nabi shallallahu 'alaihi wasallam seraya berkata: \"Wahai Rasulullah, sesungguhnya ibuku meninggal dunia sedang saat itu aku tidak ada di sisinya. Apakah akan bermanfaat baginya bila aku menshadaqahkan sesuatu untuknya?\" Beliau bersabda: \"Ya\". Dia berkata: \"Aku bersaksi kepada Tuan bahwa kebunku yang penuh dengan bebuahannya ini aku shadaqahkan atas (nama) nya","grades":[{"name":"Imam Bukhari","grade":"Sahih"}],"reference":{"book":55,"hadith":25},"chapter":{"id":20,"ara-name":"باب الإِشْهَادِ فِي الْوَقْفِ وَالصَّدَقَةِ","eng-name":"The witnesses in the foundation of an endowment or in giving in charity","isFirstHadith":true}}]}