{"metadata":{"name":"Sahih Muslim","section":{"42":{"eng-name":"The Book of Dreams","ara-name":"كتاب الرؤيا"}},"section_detail":{"42":{"hadithnumber_first":5897,"hadithnumber_last":5937,"arabicnumber_first":2261.01,"arabicnumber_last":2275}}},"hadiths":[{"hadithnumber":5927,"arabicnumber":"2268.05","text":"Jabir reported that a person came to Allah's Apostle (ﷺ) and said:Allah's Messenger, I have seen in the state of sleep as if my head had been cut off. Thereupon Allah's Apostle (ﷺ) laughed and said: When the satan plays with any one of you in the state of sleep, do not mention it to the people; and in the hadith transmitted by Abu Bakr (the words are): \"If one of you is played with, and he did not make any mention of the word: \"Satan","grades":[{"name":"Imam Muslim","grade":"Sahih"}],"reference":{"book":42,"hadith":31},"chapter":{"id":2,"ara-name":"باب لاَ يُخْبِرُ بِتَلَعُّبِ الشَّيْطَانِ بِهِ فِي الْمَنَامِ ","eng-name":"No One Should Speak Of How The Shaitan Toyed With Him In His Sleep","isFirstHadith":false}}]}