{"metadata":{"name":"Sahih Muslim","section":{"28":{"eng-name":"The Book of Oaths, Muharibin, Qasas (Retaliation), and Diyat (Blood Money)","ara-name":"كتاب القسامة والمحاربين والقصاص والديات"}},"section_detail":{"28":{"hadithnumber_first":4342,"hadithnumber_last":4397,"arabicnumber_first":1669.01,"arabicnumber_last":1683}}},"hadiths":[{"hadithnumber":4390,"arabicnumber":"1681.02","text":"Telah menceritakan kepada kami [Qutaibah bin Sa'id] telah menceritakan kepada kami [Laits] dari [Ibnu Syihab] dari [Ibnu Musayyab] dari [Abu Hurairah] bahwa dia berkata, \"Rasulullah shallallahu 'alaihi wasallam pernah memberi putusan tentang janin seorang wanita bani Lahyan yang gugur (karena dicelakai), dengan denda membebaskan seorang budak yang mahal, baik budak laki-laki atau perempuan. Selang beberapa saat perempuan yang dijatuhi hukuman denda itu tiba-tiba meninggal dunia, maka Rasulullah shallallahu 'alaihi wasallam memutuskan bahwa harta warisan perempuan itu supaya dibagikan kepada ahli warisnya, yaitu anaknya dan suaminya. Sedangkan pembayaran denda dibebankan kepada famili terdekatnya si pembunuh","grades":[{"name":"Imam Muslim","grade":"Sahih"}],"reference":{"book":28,"hadith":49},"chapter":{"id":11,"ara-name":"باب دِيَةِ الْجَنِينِ وَوُجُوبِ الدِّيَةِ فِي قَتْلِ الْخَطَإِ وَشِبْهِ الْعَمْدِ عَلَى عَاقِلَةِ الْجَانِي","eng-name":"The Diyah for a fetus; and the Diyah for accidental killing and the ambiguous killing must be paid by the shahiqilah of the killer","isFirstHadith":false}}]}