{"metadata":{"name":"Sahih Muslim","section":{"43":{"eng-name":"The Book of Virtues","ara-name":"كتاب الفضائل"}},"section_detail":{"43":{"hadithnumber_first":384,"hadithnumber_last":6168,"arabicnumber_first":2276,"arabicnumber_last":2380.06}}},"hadiths":[{"hadithnumber":6110,"arabicnumber":"2356.02","text":"حفص بن غیاث اورعیسیٰ بن یونس دونوں نے اعمش سے جریر کی سند کے ساتھ انھی کی حدیث کے مانند ہمیں حدیث بیان کی ۔","grades":[{"name":"Imam Muslim","grade":"Sahih"}],"reference":{"book":43,"hadith":168},"chapter":{"id":35,"ara-name":"باب عِلْمِهِ صلى الله عليه وسلم بِاللَّهِ تَعَالَى وَشِدَّةِ خَشْيَتِهِ .","eng-name":"His Knowledge Of Allah And His Great Fear Of Him","isFirstHadith":false}}]}