{"metadata":{"name":"Sahih Muslim","section":{"2":{"eng-name":"The Book of Purification","ara-name":"كتاب الطهارة"}},"section_detail":{"2":{"hadithnumber_first":534,"hadithnumber_last":678,"arabicnumber_first":223,"arabicnumber_last":292.02}}},"hadiths":[{"hadithnumber":540,"arabicnumber":"227.01","text":"Сообщается, что Хумран,вольноотпущенник ‘Усмана сказал: «Я слышал ‘Усмана ибн ‘Аффана, который будучи возле мечети, когда к нему пришел муаззин во время послеполуденной /аср/ молитвы, он попросил воды для омовения и, совершив омовение, сказал: “Клянусь Аллахом, я непременно расскажу вам хадис, который не рассказал бы вам, если бы не аят из Книги Аллаха. Я слышал, как Посланник Аллаха ﷺ говорил: “Если человек, исповедующий ислам, совершит омовение должным образом и совершит молитву, то непременно Аллах простит ему те (грехи), что (он совершил) между ней и молитвой, которая следует за ней”»","grades":[{"name":"Imam Muslim","grade":"Sahih"}],"reference":{"book":2,"hadith":7},"chapter":{"id":4,"ara-name":"باب فَضْلِ الْوُضُوءِ وَالصَّلاَةِ عَقِبَهُ ","eng-name":"The virtue of performing wudu’ and salat","isFirstHadith":true}}]}