{"metadata":{"name":"Sunan an Nasai","section":{"27":{"eng-name":"The Book of Divorce","ara-name":"كتاب الطلاق"}},"section_detail":{"27":{"hadithnumber_first":3389,"hadithnumber_last":3560,"arabicnumber_first":3389,"arabicnumber_last":3560}}},"hadiths":[{"hadithnumber":3401,"arabicnumber":3401,"text":"Makhramah narrated that his father said:\"I heard Mahmud bin Labid say: 'The Messenger of Allah was told about a man who had divorced his wife with three simultaneous divorces. He stood up angrily and said: Is the Book of Allah being toyed with while I am still among you? Then a man stood up and said: 'O Messenger of Allah, shall I kill him?","grades":[{"name":"Abu Ghuddah","grade":"Daif"},{"name":"Al-Albani","grade":"Daif"},{"name":"Zubair Ali Zai","grade":"Isnaad Sahih"}],"reference":{"book":27,"hadith":13},"chapter":{"id":6,"ara-name":"باب الثَّلاَثِ الْمَجْمُوعَةِ وَمَا فِيهِ مِنَ التَّغْلِيظِ ","eng-name":"Three Simultaneous Divorces And A Stern Warning Against That","isFirstHadith":true}}]}