{"metadata":{"name":"Sharh Ma'āni Al-Āthār","section":{"6":{"eng-name":"","ara-name":"كتاب مناسك الحج"}},"section_detail":{"6":{"hadithnumber_first":3493,"arabicnumber_first":3493,"hadithnumber_last":4223,"arabicnumber_last":4223}}},"hadiths":[{"hadithnumber":4172,"arabicnumber":"4200","text":"حَدَّثَنَا يَزِيدُ بْنُ سِنَانٍ , قَالَ: ثنا بِشْرُ بْنُ عُمَرَ , قَالَ: ثنا مَالِكٌ , عَنْ نَافِعٍ , عَنِ ابْنِ عُمَرَ , فَذَكَرَ بِإِسْنَادِهِ مِثْلَهُ , غَيْرَ أَنَّهُ لَمْ يَقُلْ: «وَلَا يَخْطُبُ»","grades":[],"reference":{"book":6,"hadith":710},"chapter":{"id":35,"ara-name":"باب نكاح المحرم","eng_name":"","isFirstHadith":false}}]}