{"metadata":{"name":"Sharh Ma'āni Al-Āthār","section":{"7":{"eng-name":"","ara-name":"كتاب النكاح"}},"section_detail":{"7":{"hadithnumber_first":4224,"arabicnumber_first":4224,"hadithnumber_last":4456,"arabicnumber_last":4456}}},"hadiths":[{"hadithnumber":4272,"arabicnumber":"4300","text":"حَدَّثَنَا أَحْمَدُ بْنُ دَاوُدُ قَالَ: حَدَّثَنَا يَعْقُوبُ بْنُ حُمَيْدٍ قَالَ: ثنا سُلَيْمَانُ بْنُ حَرْبٍ قَالَ: ثنا حَمَّادُ بْنُ زَيْدٍ , عَنِ ابْنِ عَوْنٍ قَالَ: كَتَبَ إِلَيَّ نَافِعٌ أَنَّ النَّبِيَّ صَلَّى اللَّهُ عَلَيْهِ وَسَلَّمَ أَخَذَ جُوَيْرِيَةَ فِي غَزْوَةِ بَنِي الْمُصْطَلِقِ , فَأَعْتَقَهَا وَتَزَوَّجَهَا , وَجَعَلَ عِتْقَهَا صَدَاقَهَا \" أَخْبَرَنِي بِذَلِكَ عَبْدُ اللهِ بْنُ عُمَرَ , وَكَانَ فِي ذَلِكَ الْجَيْشِ فَقَدْ رَوَى هَذَا ابْنُ عُمَرَ رَضِيَ اللهُ تَعَالَى عَنْهُمَا , عَنْ رَسُولِ اللهِ صَلَّى الله عَلَيْهِ وَعَلَى آلِهِ وَسَلَّمَ كَمَا ذَكَرْنَا ثُمَّ قَالَ هُوَ مِنْ بَعْدِ النَّبِيِّ صَلَّى الله عَلَيْهِ وَعَلَى آلِهِ وَسَلَّمَ فِي مِثْلِ هَذَا , أَنَّهُ يُجَدِّدُ لَهَا صَدَاقًا. ⦗٢١⦘","grades":[],"reference":{"book":7,"hadith":77},"chapter":{"id":5,"ara-name":"باب الرجل يعتق أمته على أن عتقها صداقها","eng_name":"","isFirstHadith":false}}]}