{"metadata":{"name":"Sharh Ma'āni Al-Āthār","section":{"13":{"eng-name":"","ara-name":"كتاب السير"}},"section_detail":{"13":{"hadithnumber_first":5075,"arabicnumber_first":5075,"hadithnumber_last":5479,"arabicnumber_last":5479}}},"hadiths":[{"hadithnumber":5146,"arabicnumber":"5188","text":"حَدَّثَنَا أَبُو بَكْرَةَ , قَالَ: ثنا أَبُو دَاوُدَ , قَالَ: ثنا إِسْمَاعِيلُ بْنُ عَيَّاشٍ , عَنْ صَفْوَانِ بْنِ عَمْرٍو السَّكْسَكِيِّ , عَنْ عَبْدِ الرَّحْمَنِ بْنِ جُبَيْرِ بْنِ نُفَيْرٍ , عَنْ أَبِيهِ , عَنْ خَالِدِ بْنِ الْوَلِيدِ وَعَوْفِ بْنِ مَالِكٍ أَنَّ رَسُولَ اللهِ صَلَّى اللَّهُ عَلَيْهِ وَسَلَّمَ قَضَى بِالسَّلَبِ لِلْقَاتِلِ","grades":[],"reference":{"book":13,"hadith":114},"chapter":{"id":6,"ara-name":"باب الرجل يقتل قتيلا في دار الحرب , هل يكون له سلبه أم لا؟","eng_name":"","isFirstHadith":false}}]}