{"metadata":{"name":"Sahih al Bukhari","section":{"62":{"eng-name":"Companions of the Prophet","ara-name":"كتاب فضائل أصحاب النبى صلى الله عليه وسلم"}},"section_detail":{"62":{"hadithnumber_first":3649,"hadithnumber_last":3775,"arabicnumber_first":3649,"arabicnumber_last":3775}}},"hadiths":[{"hadithnumber":3655,"arabicnumber":3655,"text":"حدثنا عبد العزيز بن عبد الله، حدثنا سليمان، عن يحيى بن سعيد، عن نافع، عن ابن عمر رضى الله عنهما قال كنا نخير بين الناس في زمن النبي صلى الله عليه وسلم فنخير ابا بكر، ثم عمر بن الخطاب، ثم عثمان بن عفان رضى الله عنهم","grades":[{"name":"Imam Bukhari","grade":"Sahih"}],"reference":{"book":62,"hadith":7},"chapter":{"id":4,"ara-name":"باب فَضْلِ أَبِي بَكْرٍ بَعْدَ النَّبِيِّ صلى الله عليه وسلم","eng-name":"The merits of Abu Bakr رضي الله عنه","isFirstHadith":true}}]}