{"metadata":{"name":"Sahih al Bukhari","section":{"64":{"eng-name":"Military Expeditions led by the Prophet (pbuh) (Al-Maghaazi)","ara-name":"كتاب المغازى"}},"section_detail":{"64":{"hadithnumber_first":3949,"hadithnumber_last":4473,"arabicnumber_first":3949,"arabicnumber_last":4473}}},"hadiths":[{"hadithnumber":3960,"arabicnumber":3960,"text":"حدثني عمرو بن خالد، حدثنا زهير، حدثنا ابو اسحاق، عن عمرو بن ميمون، عن عبد الله بن مسعود رضى الله عنه قال استقبل النبي صلى الله عليه وسلم الكعبة فدعا على نفر من قريش، على شيبة بن ربيعة، وعتبة بن ربيعة والوليد بن عتبة، وابي جهل بن هشام. فاشهد بالله لقد رايتهم صرعى، قد غيرتهم الشمس، وكان يوما حارا","grades":[{"name":"Imam Bukhari","grade":"Sahih"}],"reference":{"book":64,"hadith":12},"chapter":{"id":7,"ara-name":"باب دُعَاءُ النَّبِيِّ صلى الله عليه وسلم عَلَى كُفَّارِ قُرَيْشٍ شَيْبَةَ وَعُتْبَةَ وَالْوَلِيدِ وَأَبِي جَهْلِ بْنِ هِشَامٍ وَهَلَاكِهِمْ","eng-name":"Invoking evil of the Prophet (ﷺ) on the disbelievers of Quraish and their death","isFirstHadith":true}}]}