{"metadata":{"name":"Sahih al Bukhari","section":{"64":{"eng-name":"Military Expeditions led by the Prophet (pbuh) (Al-Maghaazi)","ara-name":"كتاب المغازى"}},"section_detail":{"64":{"hadithnumber_first":3949,"hadithnumber_last":4473,"arabicnumber_first":3949,"arabicnumber_last":4473}}},"hadiths":[{"hadithnumber":4050,"arabicnumber":4050,"text":"حدثنا ابو الوليد، حدثنا شعبة، عن عدي بن ثابت، سمعت عبد الله بن يزيد،، يحدث عن زيد بن ثابت رضى الله عنه قال لما خرج النبي صلى الله عليه وسلم الى احد، رجع ناس ممن خرج معه، وكان اصحاب النبي صلى الله عليه وسلم فرقتين، فرقة تقول نقاتلهم. وفرقة تقول لا نقاتلهم. فنزلت {فما لكم في المنافقين فيتين والله اركسهم بما كسبوا} وقال \" انها طيبة تنفي الذنوب كما تنفي النار خبث الفضة","grades":[{"name":"Imam Bukhari","grade":"Sahih"}],"reference":{"book":64,"hadith":96},"chapter":{"id":17,"ara-name":"باب غَزْوَةِ أُحُدٍ","eng-name":"The Ghazwa of Uhud","isFirstHadith":false}}]}