{"metadata":{"name":"Sahih al Bukhari","section":{"91":{"eng-name":"Interpretation of Dreams","ara-name":"كتاب التعبير"}},"section_detail":{"91":{"hadithnumber_first":6982,"hadithnumber_last":7047,"arabicnumber_first":6982,"arabicnumber_last":7047}}},"hadiths":[{"hadithnumber":7008,"arabicnumber":7008,"text":"حدثنا علي بن عبد الله، حدثنا يعقوب بن ابراهيم، حدثني ابي، عن صالح، عن ابن شهاب، قال حدثني ابو امامة بن سهل، انه سمع ابا سعيد الخدري، يقول قال رسول الله صلى الله عليه وسلم \" بينما انا نايم رايت الناس يعرضون على، وعليهم قمص، منها ما يبلغ الثدى، ومنها ما يبلغ دون ذلك، ومر على عمر بن الخطاب وعليه قميص يجره \". قالوا ما اولت يا رسول الله قال \" الدين","grades":[{"name":"Imam Bukhari","grade":"Sahih"}],"reference":{"book":91,"hadith":26},"chapter":{"id":17,"ara-name":"باب الْقَمِيصِ فِي الْمَنَامِ","eng-name":"A shirt in a dream","isFirstHadith":true}}]}