{"metadata":{"name":"Sahih al Bukhari","section":{"56":{"eng-name":"Fighting for the Cause of Allah (Jihaad)","ara-name":"كتاب الجهاد والسير"}},"section_detail":{"56":{"hadithnumber_first":2782,"hadithnumber_last":3090,"arabicnumber_first":2782,"arabicnumber_last":3090}}},"hadiths":[{"hadithnumber":2838,"arabicnumber":2838,"text":"حَدَّثَنَا أَحْمَدُ بْنُ يُونُسَ، حَدَّثَنَا زُهَيْرٌ، حَدَّثَنَا حُمَيْدٌ، أَنَّ أَنَسًا، حَدَّثَهُمْ قَالَ رَجَعْنَا مِنْ غَزْوَةِ تَبُوكَ مَعَ النَّبِيِّ صلى الله عليه وسلم‏.‏","grades":[{"name":"Imam Bukhari","grade":"Sahih"}],"reference":{"book":56,"hadith":54},"chapter":{"id":35,"ara-name":"باب مَنْ حَبَسَهُ الْعُذْرُ عَنِ الْغَزْوِ","eng-name":"Whoever is held back from Jihad by a legal cause","isFirstHadith":true}}]}