{"metadata":{"name":"Sahih Muslim","section":{"39":{"eng-name":"The Book of Greetings","ara-name":"كتاب السلام"}},"section_detail":{"39":{"hadithnumber_first":5646,"hadithnumber_last":5861,"arabicnumber_first":2160,"arabicnumber_last":2245.02}}},"hadiths":[{"hadithnumber":5776,"arabicnumber":"2218.05","text":"وَحَدَّثَنَا أَبُو الرَّبِيعِ، سُلَيْمَانُ بْنُ دَاوُدَ وَقُتَيْبَةُ بْنُ سَعِيدٍ قَالاَ حَدَّثَنَا حَمَّادٌ، وَهُوَ ابْنُ زَيْدٍ ح وَحَدَّثَنَا أَبُو بَكْرِ بْنُ أَبِي شَيْبَةَ، حَدَّثَنَا سُفْيَانُ بْنُ عُيَيْنَةَ، كِلاَهُمَا عَنْ عَمْرِو بْنِ، دِينَارٍ بِإِسْنَادِ ابْنِ جُرَيْجٍ نَحْوَ حَدِيثِهِ ‏.‏","grades":[{"name":"Imam Muslim","grade":"Sahih"}],"reference":{"book":39,"hadith":128},"chapter":{"id":32,"ara-name":"باب الطَّاعُونِ وَالطِّيَرَةِ وَالْكَهَانَةِ وَنَحْوِهَا ","eng-name":"The Plague, Ill Omens, Soothsaying And The Like","isFirstHadith":false}}]}