{"metadata":{"name":"Sahih al Bukhari","section":{"60":{"eng-name":"Prophets","ara-name":"كتاب أحاديث الأنبياء"}},"section_detail":{"60":{"hadithnumber_first":3326,"hadithnumber_last":3488,"arabicnumber_first":3326,"arabicnumber_last":3488}}},"hadiths":[{"hadithnumber":3428,"arabicnumber":3428,"text":"Abdullah dedi ki: \"İman edenlere ve imanlarına zulüm karıştırmayanlara gelince ... \"[En'am, 82] buyruğu nazil olunca Nebi Sallallahu Aleyhi ve Sellem'in ashabı: Hangimiz imanına zulüm karıştırmaz ki, dediler. Bunun üzerine: \"Allah'a ortak koşma! Şüphesiz şirk pek büyük bir zuıümdür.\"[Lukman, 13] ayeti nazil oldu","grades":[{"name":"Imam Bukhari","grade":"Sahih"}],"reference":{"book":60,"hadith":99},"chapter":{"id":41,"ara-name":"بَابُ قَوْلُ اللَّهِ تَعَالَى: {وَلَقَدْ آتَيْنَا لُقْمَانَ الْحِكْمَةَ أَنِ اشْكُرْ لِلَّهِ} إِلَى قَوْلِهِ: {إِنَّ اللَّهَ لاَ يُحِبُّ كُلَّ مُخْتَالٍ فَخُورٍ}","eng-name":"The Statement of Allah Taa'la: \"And indeed We bestowed upon Luqman Al-Hikmah...\"","isFirstHadith":true}}]}