{"metadata":{"name":"Sahih al Bukhari","section":{"2":{"eng-name":"Belief","ara-name":"كتاب الإيمان"}},"section_detail":{"2":{"hadithnumber_first":8,"hadithnumber_last":58,"arabicnumber_first":8,"arabicnumber_last":58}}},"hadiths":[{"hadithnumber":8,"arabicnumber":8,"text":"Нам рассказал ‘Убейдулла ибн Муса, сказавший: Нам сообщил Ханзала ибн Абу Суфйан, от ‘Икримы ибн Халида от Ибн ‘Умара, да будет доволен Аллах ими обоими, сказавшего: сказал: «Посланник Аллаха ﷺ сказал: “Ислам основывается на пяти (столпах): свидетельстве о том, что нет божества, достойного поклонения, кроме Аллаха, и что Мухаммад — Посланник Аллаха, совершении молитвы, выплате закята, совершении хаджа и соблюдении поста в рамадане”»","grades":[{"name":"Imam Bukhari","grade":"Sahih"}],"reference":{"book":2,"hadith":1},"chapter":{"id":2,"ara-name":"باب دُعَاؤُكُمْ إِيمَانُكُمْ","eng-name":"Your invocation means your faith","isFirstHadith":true}}]}