{"metadata":{"name":"Musnad Imam Ahmad ibn Hanbal","section":{"31":{"eng-name":"مسند أبي سعيد الخدري رضي الله عنه","ara-name":""}},"section_detail":{"31":{"hadithnumber_first":10985,"hadithnumber_last":11940,"arabicnumber_first":10985,"arabicnumber_last":11940}}},"hadiths":[{"hadithnumber":11375,"arabicnumber":11375,"text":"حَدَّثَنَا يُونُسُ، حَدَّثَنَا لَيْثٌ، عَنْ يَزِيدَ بْنِ أَبِي حَبِيبٍ، عَنْ أَبِي النَّضْرِ، أَنَّ أَبَا سَعِيدٍ الْخُدْرِيَّ، كَانَ يَشْتَكِي رِجْلَهُ، فَدَخَلَ عَلَيْهِ أَخُوهُ (٤) وَقَدْ جَعَلَ إِحْدَى رِجْلَيْهِ عَلَى الْأُخْرَى وَهُوَ مُضْطَجِعٌ، فَضَرَبَهُ بِيَدِهِ، ، عَلَى رِجْلِهِ الْوَجِعَةِ فَأَوْجَعَهُ، فَقَالَ: أَوْجَعْتَنِي، أَوَلَمْ تَعْلَمْ أَنَّ رِجْلِي وَجِعَةٌ؟ قَالَ: بَلَى، قَالَ: فَمَا حَمَلَكَ عَلَى ذَلِكَ؟ قَالَ: \" أَوَلَمْ تَسْمَعْ أَنَّ النَّبِيَّ صَلَّى اللهُ عَلَيْهِ وَسَلَّمَ قَدْ نَهَى عَنْ هَذِهِ \"؟ (١)،","grades":[],"reference":{"book":31,"hadith":391},"chapter":{"id":null,"ara-name":null,"eng_name":null,"isFirstHadith":null}}]}