{"metadata":{"name":"Musnad Imam Ahmad ibn Hanbal","section":{"31":{"eng-name":"مسند أبي سعيد الخدري رضي الله عنه","ara-name":""}},"section_detail":{"31":{"hadithnumber_first":10985,"hadithnumber_last":11940,"arabicnumber_first":10985,"arabicnumber_last":11940}}},"hadiths":[{"hadithnumber":11730,"arabicnumber":11730,"text":"حَدَّثَنَا يَعْقُوبُ، حَدَّثَنَا أَبِي، عَنْ ابْنِ إِسْحَاقَ قَالَ: وَحَدَّثَنِي عَاصِمُ بْنُ عُمَرَ بْنِ قَتَادَةَ، عَنْ مَحْمُودِ بْنِ لَبِيدٍ، عَنْ أَبِي سَعِيدٍ الْخُدْرِيِّ قَالَ: لَمَّا أَعْطَى رَسُولُ اللهِ صَلَّى اللهُ عَلَيْهِ وَسَلَّمَ مَا أَعْطَى مِنْ تِلْكَ الْعَطَايَا فِي قُرَيْشٍ وَقَبَائِلِ الْعَرَبِ، وَلَمْ يَكُنْ (٣) فِي الْأَنْصَارِ مِنْهَا شَيْءٌ وَجَدَ هَذَا الْحَيُّ مِنَ الْأَنْصَارِ فِي أَنْفُسِهِمْ، حَتَّى كَثُرَتْ فِيهِمُ الْقَالَةُ حَتَّى قَالَ قَائِلُهُمْ: لَقِيَ (٤) رَسُولُ اللهِ صَلَّى اللهُ عَلَيْهِ وَسَلَّمَ قَوْمَهُ، فَدَخَلَ عَلَيْهِ سَعْدُ بْنُ عُبَادَةَ، فَقَالَ: يَا رَسُولَ اللهِ، إِنَّ هَذَا الْحَيَّ قَدْ، ، وَجَدُوا عَلَيْكَ فِي أَنْفُسِهِمْ لِمَا صَنَعْتَ فِي هَذَا الْفَيْءِ الَّذِي أَصَبْتَ، قَسَمْتَ فِي قَوْمِكَ، وَأَعْطَيْتَ (١) عَطَايَا عِظَامًا فِي قَبَائِلِ الْعَرَبِ، وَلَمْ يَكُ فِي هَذَا الْحَيِّ مِنَ الْأَنْصَارِ شَيْءٌ، قَالَ: \" فَأَيْنَ أَنْتَ مِنْ ذَلِكَ يَا سَعْدُ؟ \" قَالَ: يَا رَسُولَ اللهِ، مَا أَنَا إِلَّا امْرُؤٌ مِنْ قَوْمِي، وَمَا أَنَا؟ قَالَ: \" فَاجْمَعْ لِي قَوْمَكَ فِي هَذِهِ الْحَظِيرَةِ \"، قَالَ: فَخَرَجَ سَعْدٌ، فَجَمَعَ الْأَنْصَارَ (٢) فِي تِلْكَ الْحَظِيرَةِ، قَالَ: فَجَاءَ رِجَالٌ مِنَ الْمُهَاجِرِينَ، فَتَرَكَهُمْ، فَدَخَلُوا وَجَاءَ آخَرُونَ، فَرَدَّهُمْ، فَلَمَّا اجْتَمَعُوا أَتَاهُ سَعْدٌ فَقَالَ: قَدِ اجْتَمَعَ لَكَ هَذَا الْحَيُّ مِنَ الْأَنْصَارِ، قَالَ: فَأَتَاهُمْ رَسُولُ اللهِ صَلَّى اللهُ عَلَيْهِ وَسَلَّمَ فَحَمِدَ اللهَ وَأَثْنَى عَلَيْهِ، بِالَّذِي هُوَ لَهُ أَهْلٌ، ثُمَّ قَالَ: \" يَا مَعْشَرَ (٣) الْأَنْصَارِ مَا قَالَةٌ بَلَغَتْنِي عَنْكُمْ وَجِدَةٌ وَجَدْتُمُوهَا فِي أَنْفُسِكُمْ، أَلَمْ آتِكُمْ ضُلَّالًا فَهَدَاكُمُ اللهُ؟ وَعَالَةً فَأَغْنَاكُمُ اللهُ؟ وَأَعْدَاءً فَأَلَّفَ اللهُ بَيْنَ قُلُوبِكُمْ؟ \"، قَالُوا: بَلِ (٤) اللهُ وَرَسُولُهُ أَمَنُّ وَأَفْضَلُ. قَالَ: \" أَلَا تُجِيبُونَنِي يَا مَعْشَرَ الْأَنْصَارِ \" قَالُوا: وَبِمَاذَا نُجِيبُكَ يَا رَسُولَ اللهِ، وَلِلَّهِ وَلِرَسُولِهِ الْمَنُّ وَالْفَضْلُ. قَالَ: \" أَمَا وَاللهِ لَوْ شِئْتُمْ لَقُلْتُمْ فَلَصَدَقْتُمْ وَصُدِّقْتُمْ (٥) ، أَتَيْتَنَا مُكَذَّبًا فَصَدَّقْنَاكَ، وَمَخْذُولًا فَنَصَرْنَاكَ،، ، وَطَرِيدًا فَآوَيْنَاكَ، وَعَائِلًا فَآسَيْنَاكَ (١) ، أَوَجَدْتُمْ فِي أَنْفُسِكُمْ يَا مَعْشَرَ الْأَنْصَارِ فِي لُعَاعَةٍ مِنَ الدُّنْيَا، تَأَلَّفْتُ بِهَا قَوْمًا لِيُسْلِمُوا، وَوَكَلْتُكُمْ (٢) إِلَى إِسْلَامِكُمْ؟ أَفَلَا تَرْضَوْنَ يَا مَعْشَرَ الْأَنْصَارِ أَنْ يَذْهَبَ النَّاسُ بِالشَّاةِ وَالْبَعِيرِ، وَتَرْجِعُونَ بِرَسُولِ اللهِ فِي رِحَالِكُمْ؟ فَوَالَّذِي نَفْسُ مُحَمَّدٍ بِيَدِهِ لَوْلَا (٣) الْهِجْرَةُ لَكُنْتُ امْرَأً مِنَ الْأَنْصَارِ، وَلَوْ سَلَكَ النَّاسُ شِعْبًا، وَسَلَكَتِ الْأَنْصَارُ شِعْبًا لَسَلَكْتُ شِعْبَ الْأَنْصَارِ، اللهُمَّ ارْحَمِ الْأَنْصَارَ، وَأَبْنَاءَ الْأَنْصَارِ، وَأَبْنَاءَ أَبْنَاءِ الْأَنْصَارِ \" قَالَ: فَبَكَى الْقَوْمُ، حَتَّى أَخْضَلُوا لِحَاهُمْ، وَقَالُوا: رَضِينَا بِرَسُولِ اللهِ قِسْمًا وَحَظًّا، ثُمَّ انْصَرَفَ رَسُولُ اللهِ صَلَّى اللهُ عَلَيْهِ وَسَلَّمَ وَتَفَرَّقُوا (٤)، ،","grades":[],"reference":{"book":31,"hadith":746},"chapter":{"id":null,"ara-name":null,"eng_name":null,"isFirstHadith":null}}]}