{"metadata":{"name":"Musnad Imam Ahmad ibn Hanbal","section":{"33":{"eng-name":"مسند جابر بن عبد الله رضي الله عنه","ara-name":""}},"section_detail":{"33":{"hadithnumber_first":14112,"hadithnumber_last":15299,"arabicnumber_first":14112,"arabicnumber_last":15299}}},"hadiths":[{"hadithnumber":14141,"arabicnumber":14141,"text":"حَدَّثَنَا عَبْدُ الرَّزَّاقِ، أَخْبَرَنَا ابْنُ جُرَيْجٍ، أَخْبَرَنِي أَبُو الزُّبَيْرِ، أَنَّهُ: سَمِعَ جَابِرَ بْنَ عَبْدِ اللهِ، يَقُولُ: سَمِعْتُ رَسُولَ اللهِ صَلَّى اللهُ عَلَيْهِ وَسَلَّمَ يَقُولُ: \" أُقَاتِلُ النَّاسَ حَتَّى يَقُولُوا: لَا إِلَهَ إِلَّا اللهُ، فَإِذَا فَعَلُوا ذَلِكَ، عَصَمُوا دِمَاءَهُمْ وَأَمْوَالَهُمْ إِلَّا بِحَقِّهَا، وَحِسَابُهُمْ عَلَى اللهِ \" (١)، ،","grades":[],"reference":{"book":33,"hadith":30},"chapter":{"id":null,"ara-name":null,"eng_name":null,"isFirstHadith":null}}]}