{"metadata":{"name":"Musnad Imam Ahmad ibn Hanbal","section":{"33":{"eng-name":"مسند جابر بن عبد الله رضي الله عنه","ara-name":""}},"section_detail":{"33":{"hadithnumber_first":14112,"hadithnumber_last":15299,"arabicnumber_first":14112,"arabicnumber_last":15299}}},"hadiths":[{"hadithnumber":14626,"arabicnumber":14626,"text":"حَدَّثَنَا حَسَنٌ، حَدَّثَنَا ابْنُ لَهِيعَةَ، حَدَّثَنَا أَبُو الزُّبَيْرِ، عَنْ جَابِرٍ، قَالَ: قَالَ رَسُولُ اللهِ صَلَّى اللهُ عَلَيْهِ وَسَلَّمَ: \" أَكْثِرُوا مِنْ هَذِهِ النِّعَالِ، فَإِنَّهُ لَا يَزَالُ أَحَدُكُمْ رَاكِبًا إِذَا انْتَعَلَ \"، ،","grades":[],"reference":{"book":33,"hadith":515},"chapter":{"id":null,"ara-name":null,"eng_name":null,"isFirstHadith":null}}]}