{"metadata":{"name":"Musnad Imam Ahmad ibn Hanbal","section":{"304":{"eng-name":"حديث عثمان بن أبي العاص الثقفي","ara-name":""}},"section_detail":{"304":{"hadithnumber_first":16268,"hadithnumber_last":16282,"arabicnumber_first":16268,"arabicnumber_last":16282}}},"hadiths":[{"hadithnumber":16279,"arabicnumber":16279,"text":"وَسَمِعْتُ رَسُولَ اللهِ صَلَّى اللهُ عَلَيْهِ وَسَلَّمَ يَقُولُ: \" صِيَامٌ حَسَنٌ صِيَامُ ثَلَاثَةِ أَيَّامٍ مِنَ الشَّهْرِ \" (٢)،","grades":[],"reference":{"book":304,"hadith":12},"chapter":{"id":null,"ara-name":null,"eng_name":null,"isFirstHadith":null}}]}