{"metadata":{"name":"Musnad Imam Ahmad ibn Hanbal","section":{"1024":{"eng-name":"حديث أبي زيد عمرو بن أخطب","ara-name":""}},"section_detail":{"1024":{"hadithnumber_first":22881,"hadithnumber_last":22892,"arabicnumber_first":22881,"arabicnumber_last":22892}}},"hadiths":[{"hadithnumber":22882,"arabicnumber":22882,"text":"حَدَّثَنَا زَيْدُ بْنُ الْحُبَابِ، حَدَّثَنِي حُسَيْنُ بْنُ وَاقِدٍ قَالَ: سَمِعْتُ أَبَا نَهِيكٍ يَقُولُ: سَمِعْتُ أَبَا زَيْدٍ عَمْرَو بْنَ أَخْطَبَ قَالَ: \" رَأَيْتُ الْخَاتَمَ الَّذِي بَيْنَ كَتِفَيْ رَسُولِ اللهِ صَلَّى اللهُ عَلَيْهِ وَسَلَّمَ كَرَجُلٍ، قَالَ بِإِصْبَعِهِ الثَّالِثَةِ (٢) هَكَذَا،، ، فَمَسَحْتُهُ بِيَدِي \" (١)،","grades":[],"reference":{"book":1024,"hadith":2},"chapter":{"id":null,"ara-name":null,"eng_name":null,"isFirstHadith":null}}]}