{"metadata":{"name":"Musnad Imam Ahmad ibn Hanbal","section":{"1028":{"eng-name":"أحاديث رجال من أصحاب النبي صلى الله عليه وسلم","ara-name":""}},"section_detail":{"1028":{"hadithnumber_first":23062,"hadithnumber_last":23198,"arabicnumber_first":23062,"arabicnumber_last":23198}}},"hadiths":[{"hadithnumber":23085,"arabicnumber":23085,"text":"حَدَّثَنَا وَكِيعٌ، حَدَّثَنَا الْأَعْمَشُ، عَنْ أَبِي صَالِحٍ ذَكْوَانَ، عَنْ بَعْضِ أَصْحَابِ النَّبِيِّ صَلَّى اللهُ عَلَيْهِ وَسَلَّمَ قَالَ: جَاءَ رَجُلٌ إِلَى النَّبِيِّ صَلَّى اللهُ عَلَيْهِ وَسَلَّمَ فَقَالَ: يَا رَسُولَ اللهِ، إِنَّ لِفُلَانٍ نَخْلَةً فِي حَائِطِي، فَمُرْهُ فَلْيَبِعْنِيهَا، أَوْ لِيَهَبْهَا لِي، قَالَ: فَأَبَى الرَّجُلُ، فَقَالَ رَسُولُ اللهِ صَلَّى اللهُ عَلَيْهِ وَسَلَّمَ: \" افْعَلْ وَلَكَ بِهَا نَخْلَةٌ فِي الْجَنَّةِ \"، فَأَبَى، فَقَالَ النَّبِيُّ صَلَّى اللهُ عَلَيْهِ وَسَلَّمَ: \" هَذَا أَبْخَلُ النَّاسِ \" (٢)، ،","grades":[],"reference":{"book":1028,"hadith":24},"chapter":{"id":null,"ara-name":null,"eng_name":null,"isFirstHadith":null}}]}