{"metadata":{"name":"Musnad Imam Ahmad ibn Hanbal","section":{"1028":{"eng-name":"أحاديث رجال من أصحاب النبي صلى الله عليه وسلم","ara-name":""}},"section_detail":{"1028":{"hadithnumber_first":23062,"hadithnumber_last":23198,"arabicnumber_first":23062,"arabicnumber_last":23198}}},"hadiths":[{"hadithnumber":23188,"arabicnumber":23188,"text":"حَدَّثَنَا حَجَّاجٌ، حَدَّثَنَا شُعْبَةُ، عَنْ سَعِيدٍ الْجُرَيْرِيِّ قَالَ: سَمِعْتُ عُبَيْدَ بْنَ الْقَعْقَاعِ يُحَدِّثُ رَجُلًا مِنْ بَنِي حَنْظَلَةَ قَالَ:، ، رَمَقَ رَجُلٌ رَسُولَ اللهِ صَلَّى اللهُ عَلَيْهِ وَسَلَّمَ وَهُوَ يُصَلِّي فَجَعَلَ يَقُولُ فِي صَلَاتِهِ: \" اللهُمَّ اغْفِرْ لِي ذَنْبِي، وَوَسِّعْ لِي فِي ذَاتِي، وَبَارِكْ لِي فِيمَا رَزَقْتَنِي \" (١)،","grades":[],"reference":{"book":1028,"hadith":127},"chapter":{"id":null,"ara-name":null,"eng_name":null,"isFirstHadith":null}}]}