{"metadata":{"name":"Musnad Imam Ahmad ibn Hanbal","section":{"1165":{"eng-name":"مسند الصديقة عائشة بنت الصديق رضي الله عنها","ara-name":""}},"section_detail":{"1165":{"hadithnumber_first":24043,"hadithnumber_last":26412,"arabicnumber_first":24043,"arabicnumber_last":26412}}},"hadiths":[{"hadithnumber":25601,"arabicnumber":25601,"text":"حَدَّثَنَا يَحْيَى، عَنْ هِشَامٍ، قَالَ: أَخْبَرَنِي أَبِي قَالَ أَخْبَرَتْنِي عَائِشَةُ قَالَتْ: \" كُفِّنَ النَّبِيُّ صَلَّى اللهُ عَلَيْهِ وَسَلَّمَ فِي ثَلَاثَةِ أَثْوَابٍ يَمَانِيَةٍ، بِيضٍ لَيْسَ فِيهَا قَمِيصٌ وَلَا عِمَامَةٌ \" (١)،","grades":[],"reference":{"book":1165,"hadith":1559},"chapter":{"id":null,"ara-name":null,"eng_name":null,"isFirstHadith":null}}]}