{"metadata":{"name":"Musnad Imam Ahmad ibn Hanbal","section":{"1165":{"eng-name":"مسند الصديقة عائشة بنت الصديق رضي الله عنها","ara-name":""}},"section_detail":{"1165":{"hadithnumber_first":24043,"hadithnumber_last":26412,"arabicnumber_first":24043,"arabicnumber_last":26412}}},"hadiths":[{"hadithnumber":26032,"arabicnumber":26032,"text":"حَدَّثَنَا يَزِيدُ، قَالَ: أَخْبَرَنَا إِبْرَاهِيمُ بْنُ سَعْدٍ، قَالَ: حَدَّثَنِي أَبِي، عَنْ عُرْوَةَ بْنِ الزُّبَيْرِ، عَنْ عَائِشَةَ، قَالَتْ: \" لَمَّا مَرِضَ رَسُولُ اللهِ صَلَّى اللهُ عَلَيْهِ وَسَلَّمَ دَعَا ابْنَتَهُ فَاطِمَةَ فَسَارَّهَا فَبَكَتْ، ثُمَّ سَارَّهَا فَضَحِكَتْ، فَسَأَلْتُهَا عَنْ ذَلِكَ، فَقَالَتْ: أَمَّا حَيْثُ بَكَيْتُ، فَإِنَّهُ أَخْبَرَنِي: أَنَّهُ مَيِّتٌ فَبَكَيْتُ، ثُمَّ أَخْبَرَنِي: \" أَنِّي أَوَّلُ أَهْلِهِ (١) لُحُوقًا بِهِ فَضَحِكْتُ \" (٢)،","grades":[],"reference":{"book":1165,"hadith":1990},"chapter":{"id":null,"ara-name":null,"eng_name":null,"isFirstHadith":null}}]}