{"metadata":{"name":"Musnad Imam Ahmad ibn Hanbal","section":{"1168":{"eng-name":"حديث أم سلمة زوج النبي صلى الله عليه وسلم","ara-name":""}},"section_detail":{"1168":{"hadithnumber_first":26471,"hadithnumber_last":26750,"arabicnumber_first":26471,"arabicnumber_last":26750}}},"hadiths":[{"hadithnumber":26484,"arabicnumber":26484,"text":"حَدَّثَنَا عَبْدُ الرَّحْمَنِ يَعْنِي ابْنَ مَهْدِيٍّ، عَنْ (١) مَالِكٍ عَنْ سُمَيٍّ، وَعَبْدِ رَبِّهِ، عَنْ أَبِي بَكْرِ بْنِ (٢) عَبْدِ الرَّحْمَنِ، عَنْ عَائِشَةَ، وَأُمِّ سَلَمَةَ أَنَّ رَسُولَ اللهِ صَلَّى اللهُ عَلَيْهِ وَسَلَّمَ كَانَ يُصْبِحُ جُنُبًا مِنْ جِمَاعٍ غَيْرِ احْتِلَامٍ، ثُمَّ يَصُومُ \" وَفِي حَدِيثِ عَبْدِ رَبِّهِ: فِي رَمَضَانَ (٣)،","grades":[],"reference":{"book":1168,"hadith":14},"chapter":{"id":null,"ara-name":null,"eng_name":null,"isFirstHadith":null}}]}