{"metadata":{"name":"Musnad Imam Ahmad ibn Hanbal","section":{"27":{"eng-name":"مسند عبد الله بن عمر رضي الله عنهما","ara-name":""}},"section_detail":{"27":{"hadithnumber_first":4448,"hadithnumber_last":6476,"arabicnumber_first":4448,"arabicnumber_last":6476}}},"hadiths":[{"hadithnumber":4477,"arabicnumber":4477,"text":"حَدَّثَنَا إِسْمَاعِيلُ، حَدَّثَنَا أَيُّوبُ، عَنْ سَعِيدِ بْنِ جُبَيْرٍ، قَالَ: قُلْتُ لِابْنِ عُمَرَ: رَجُلٌ قَذَفَ امْرَأَتَهُ فَقَالَ: فَرَّقَ رَسُولُ اللهِ صَلَّى اللهُ عَلَيْهِ وَسَلَّمَ بَيْنَ أَخَوَيْ بَنِي الْعَجْلَانِ، وَقَالَ: \" اللهُ يَعْلَمُ أَنَّ أَحَدَكُمَا كَاذِبٌ، فَهَلْ مِنْكُمَا تَائِبٌ؟ \" فَأَبَيَا فَرَدَّدَهُمَا (١) ثَلَاثَ مَرَّاتٍ، فَأَبَيَا، فَفَرَّقَ بَيْنَهُمَا (٢)، ،","grades":[],"reference":{"book":27,"hadith":30},"chapter":{"id":null,"ara-name":null,"eng_name":null,"isFirstHadith":null}}]}