{"metadata":{"name":"Musnad Imam Ahmad ibn Hanbal","section":{"27":{"eng-name":"مسند عبد الله بن عمر رضي الله عنهما","ara-name":""}},"section_detail":{"27":{"hadithnumber_first":4448,"hadithnumber_last":6476,"arabicnumber_first":4448,"arabicnumber_last":6476}}},"hadiths":[{"hadithnumber":6200,"arabicnumber":6200,"text":"حَدَّثَنَا مُحَمَّدُ بْنُ كُنَاسَةَ، حَدَّثَنَا إِسْحَاقُ بْنُ سَعِيدٍ، عَنْ أَبِيهِ قَالَ: أَتَى عَبْدُ اللهِ بْنُ عُمَرَ عَبْدَ اللهِ بْنَ الزُّبَيْرِ، فَقَالَ: يَا ابْنَ الزُّبَيْرِ: إِيَّاكَ وَالْإِلْحَادَ فِي حَرَمِ اللهِ تَبَارَكَ وَتَعَالَى، فَإِنِّي سَمِعْتُ رَسُولَ اللهِ صَلَّى اللهُ عَلَيْهِ وَسَلَّمَ يَقُولُ: \" إِنَّهُ سَيُلْحِدُ فِيهِ رَجُلٌ مِنْ قُرَيْشٍ، لَوْ وُزِنَتْ (١) ذُنُوبُهُ بِذُنُوبِ الثَّقَلَيْنِ لَرَجَحَتْ \" قَالَ: فَانْظُرْ لَا تَكُونُهُ (٢)،","grades":[],"reference":{"book":27,"hadith":1753},"chapter":{"id":null,"ara-name":null,"eng_name":null,"isFirstHadith":null}}]}