{"metadata":{"name":"Musnad Imam Ahmad ibn Hanbal","section":{"5":{"eng-name":"مسند علي بن أبي طالب رضي الله عنه","ara-name":""}},"section_detail":{"5":{"hadithnumber_first":562,"hadithnumber_last":1380,"arabicnumber_first":562,"arabicnumber_last":1380}}},"hadiths":[{"hadithnumber":995,"arabicnumber":995,"text":"حَدَّثَنَا يَحْيَى، عَنِ ابْنِ أَبِي لَيْلَى، حَدَّثَنِي أَخِي، عَنْ أَبِي، عَنْ عَلِيٍّ، عَنِ النَّبِيِّ صَلَّى اللهُ عَلَيْهِ وَسَلَّمَ قَالَ: \" إِذَا عَطَسَ أَحَدُكُمْ فَلْيَقُلْ: الْحَمْدُ لِلَّهِ عَلَى كُلِّ حَالٍ، وَلْيُقَلْ لَهُ: يَرْحَمُكُمِ اللهُ، وَلْيَقُلْ هُوَ: يَهْدِيكُمُ اللهُ، وَيُصْلِحُ بَالَكُمْ \" (٢)، ، فَقُلْتُ لَهُ: عَنْ أَبِي أَيُّوبَ؟ قَالَ: عَلِيٌّ (١)، •","grades":[],"reference":{"book":5,"hadith":434},"chapter":{"id":null,"ara-name":null,"eng_name":null,"isFirstHadith":null}}]}